{
  "generatedAt": "2026-07-01T10:57:35.650Z",
  "bySlug": {
    "braslet-iz-lunnogo-kamnya-ocharovanie": {
      "title": "Bracelet From Moon Stone Enchantment",
      "shortDescription": "Handmade bracelet for personal practice and everyday wear.",
      "description": "Handmade bracelet for personal practice and everyday wear.",
      "fullDescription": "Handmade bracelet for personal practice and everyday wear."
    },
    "altarnoe-pokryvalo": {
      "title": "Altar Cloth",
      "shortDescription": "Thoughtful magical gift or souvenir.",
      "description": "Thoughtful magical gift or souvenir.",
      "fullDescription": "Thoughtful magical gift or souvenir."
    },
    "altarnaya-podstavka-arhangel-mihail": {
      "title": "Altar Stand Archangel Michael",
      "shortDescription": "Thoughtful magical gift or souvenir.",
      "description": "Thoughtful magical gift or souvenir.",
      "fullDescription": "Thoughtful magical gift or souvenir."
    },
    "altarnaya-podstavka-chakrovaya-garmoniya": {
      "title": "Altar Stand Chakra Harmony",
      "shortDescription": "Thoughtful magical gift or souvenir.",
      "description": "Thoughtful magical gift or souvenir.",
      "fullDescription": "Thoughtful magical gift or souvenir."
    },
    "altarnaya-podstavka-arhangel-gavriil": {
      "title": "Altar Stand Archangel Gabriel",
      "shortDescription": "Thoughtful magical gift or souvenir.",
      "description": "Thoughtful magical gift or souvenir.",
      "fullDescription": "Thoughtful magical gift or souvenir."
    },
    "korobok-dlya-spichek": {
      "title": "Box For Spichek",
      "shortDescription": "Magical product for personal practice.",
      "description": "Magical product for personal practice.",
      "fullDescription": "Magical product for personal practice."
    },
    "altarnaya-podstavka-arhangel-rafail": {
      "title": "Altar Stand Archangel Raphael",
      "shortDescription": "Thoughtful magical gift or souvenir.",
      "description": "Thoughtful magical gift or souvenir.",
      "fullDescription": "Thoughtful magical gift or souvenir."
    },
    "altarnaya-podstavka-anubis": {
      "title": "Altar Stand Anubis",
      "shortDescription": "Thoughtful magical gift or souvenir.",
      "description": "Thoughtful magical gift or souvenir.",
      "fullDescription": "Thoughtful magical gift or souvenir."
    },
    "altarnaya-podstavka-arhangel-gavriil-2": {
      "title": "Altar Stand Archangel Gabriel",
      "shortDescription": "Thoughtful magical gift or souvenir.",
      "description": "Thoughtful magical gift or souvenir.",
      "fullDescription": "Thoughtful magical gift or souvenir."
    },
    "korobok-dlya-spichek-2": {
      "title": "Box For Spichek",
      "shortDescription": "Magical product for personal practice.",
      "description": "Magical product for personal practice.",
      "fullDescription": "Magical product for personal practice."
    },
    "altarnaya-podstavka-arhangel-gavriil-3": {
      "title": "Altar Stand Archangel Gabriel",
      "shortDescription": "Thoughtful magical gift or souvenir.",
      "description": "Thoughtful magical gift or souvenir.",
      "fullDescription": "Thoughtful magical gift or souvenir."
    },
    "altarnaya-podstavka-anubis-2": {
      "title": "Altar Stand Anubis",
      "shortDescription": "Thoughtful magical gift or souvenir.",
      "description": "Thoughtful magical gift or souvenir.",
      "fullDescription": "Thoughtful magical gift or souvenir."
    },
    "korobok-dlya-spichek-3": {
      "title": "Box For Spichek",
      "shortDescription": "Magical product for personal practice.",
      "description": "Magical product for personal practice.",
      "fullDescription": "Magical product for personal practice."
    },
    "altarnaya-podstavka-anubis-3": {
      "title": "Altar Stand Anubis",
      "shortDescription": "Thoughtful magical gift or souvenir.",
      "description": "Thoughtful magical gift or souvenir.",
      "fullDescription": "Thoughtful magical gift or souvenir."
    },
    "korobok-dlya-spichek-4": {
      "title": "Box For Spichek",
      "shortDescription": "Magical product for personal practice.",
      "description": "Magical product for personal practice.",
      "fullDescription": "Magical product for personal practice."
    },
    "altarnaya-podstavka-anubis-4": {
      "title": "Altar Stand Anubis",
      "shortDescription": "Thoughtful magical gift or souvenir.",
      "description": "Thoughtful magical gift or souvenir.",
      "fullDescription": "Thoughtful magical gift or souvenir."
    },
    "korobok-dlya-spichek-5": {
      "title": "Box For Spichek",
      "shortDescription": "Magical product for personal practice.",
      "description": "Magical product for personal practice.",
      "fullDescription": "Magical product for personal practice."
    },
    "altarnaya-podstavka-anubis-5": {
      "title": "Altar Stand Anubis",
      "shortDescription": "Thoughtful magical gift or souvenir.",
      "description": "Thoughtful magical gift or souvenir.",
      "fullDescription": "Thoughtful magical gift or souvenir."
    },
    "podstavka-dlya-altarya-inyan": {
      "title": "Stand For Altarya Inyan",
      "shortDescription": "Thoughtful magical gift or souvenir.",
      "description": "Thoughtful magical gift or souvenir.",
      "fullDescription": "Thoughtful magical gift or souvenir."
    },
    "altarnaya-podstavka-protsvetanie": {
      "title": "Altar Stand Protsvetanie",
      "shortDescription": "Thoughtful magical gift or souvenir.",
      "description": "Thoughtful magical gift or souvenir.",
      "fullDescription": "Thoughtful magical gift or souvenir."
    },
    "tablichka-dom-vedmy": {
      "title": "Tablichka Dom Vedmy",
      "shortDescription": "Thoughtful magical gift or souvenir.",
      "description": "Thoughtful magical gift or souvenir.",
      "fullDescription": "Thoughtful magical gift or souvenir."
    },
    "chasy-sila-volka": {
      "title": "Clock Power Volka",
      "shortDescription": "Magical product for personal practice.",
      "description": "Magical product for personal practice.",
      "fullDescription": "Magical product for personal practice."
    },
    "altarnaya-podstavka-denezhnaya-loshad": {
      "title": "Altar Stand Denezhnaya Loshad",
      "shortDescription": "Thoughtful magical gift or souvenir.",
      "description": "Thoughtful magical gift or souvenir.",
      "fullDescription": "Thoughtful magical gift or souvenir."
    },
    "bokal-drakon": {
      "title": "Goblet Drakon",
      "shortDescription": "Thoughtful magical gift or souvenir.",
      "description": "Thoughtful magical gift or souvenir.",
      "fullDescription": "Thoughtful magical gift or souvenir."
    },
    "altarnaya-podstavka-mat-zemlya": {
      "title": "Altar Stand Mat Zemlya",
      "shortDescription": "Thoughtful magical gift or souvenir.",
      "description": "Thoughtful magical gift or souvenir.",
      "fullDescription": "Thoughtful magical gift or souvenir."
    },
    "altarnoe-pokryvalo-rodovoe-drevo": {
      "title": "Altar Cloth Rodovoe Drevo",
      "shortDescription": "Magical product for personal practice.",
      "description": "Magical product for personal practice.",
      "fullDescription": "Magical product for personal practice."
    },
    "bokal-serdtse": {
      "title": "Goblet Serdtse",
      "shortDescription": "Thoughtful magical gift or souvenir.",
      "description": "Thoughtful magical gift or souvenir.",
      "fullDescription": "Thoughtful magical gift or souvenir."
    },
    "altarnoe-pokryvalo-vsevidyaschee-oko": {
      "title": "Altar Cloth Vsevidyaschee Oko",
      "shortDescription": "Magical product for personal practice.",
      "description": "Magical product for personal practice.",
      "fullDescription": "Magical product for personal practice."
    },
    "altarnoe-pokryvalo-zhenskaya-sila": {
      "title": "Altar Cloth Zhenskaya Power",
      "shortDescription": "Magical product for personal practice.",
      "description": "Magical product for personal practice.",
      "fullDescription": "Magical product for personal practice."
    },
    "altarnoe-pokryvalo-mat-zemlya": {
      "title": "Altar Cloth Mat Zemlya",
      "shortDescription": "Magical product for personal practice.",
      "description": "Magical product for personal practice.",
      "fullDescription": "Magical product for personal practice."
    },
    "altarnoe-pokryvalo-beskonechnost": {
      "title": "Altar Cloth Beskonechnost",
      "shortDescription": "Magical product for personal practice.",
      "description": "Magical product for personal practice.",
      "fullDescription": "Magical product for personal practice."
    },
    "volt": {
      "title": "Volt",
      "shortDescription": "Magical product for personal practice.",
      "description": "Magical product for personal practice.",
      "fullDescription": "Magical product for personal practice."
    },
    "altarnoe-pokryvalo-pentagramma": {
      "title": "Altar Cloth Pentagramma",
      "shortDescription": "Thoughtful magical gift or souvenir.",
      "description": "Thoughtful magical gift or souvenir.",
      "fullDescription": "Thoughtful magical gift or souvenir."
    },
    "podstavka-dlya-altarya-chakrovaya": {
      "title": "Stand For Altarya Chakra",
      "shortDescription": "Magical product for personal practice.",
      "description": "Magical product for personal practice.",
      "fullDescription": "Magical product for personal practice."
    },
    "altarnaya-podstavka-chyornyy-voron": {
      "title": "Altar Stand Chyorny Voron",
      "shortDescription": "Magical product for personal practice.",
      "description": "Magical product for personal practice.",
      "fullDescription": "Magical product for personal practice."
    },
    "altarnaya-podstavka-chyornyy-voron-2": {
      "title": "Altar Stand Chyorny Voron",
      "shortDescription": "Magical product for personal practice.",
      "description": "Magical product for personal practice.",
      "fullDescription": "Magical product for personal practice."
    },
    "altarnoe-pokryvalo-sila-vedmy": {
      "title": "Altar Cloth Power Vedmy",
      "shortDescription": "Magical product for personal practice.",
      "description": "Magical product for personal practice.",
      "fullDescription": "Magical product for personal practice."
    },
    "altarnoe-pokryvalo-pentagramma-2": {
      "title": "Altar Cloth Pentagramma",
      "shortDescription": "Magical product for personal practice.",
      "description": "Magical product for personal practice.",
      "fullDescription": "Magical product for personal practice."
    },
    "podstavka-dlya-altarya-bastet": {
      "title": "Stand For Altarya Bastet",
      "shortDescription": "Magical product for personal practice.",
      "description": "Magical product for personal practice.",
      "fullDescription": "Magical product for personal practice."
    },
    "altarnoe-pokryvalo-pentagramma-3": {
      "title": "Altar Cloth Pentagramma",
      "shortDescription": "Magical product for personal practice.",
      "description": "Magical product for personal practice.",
      "fullDescription": "Magical product for personal practice."
    },
    "podstavka-dlya-altarya-bastet-2": {
      "title": "Stand For Altarya Bastet",
      "shortDescription": "Magical product for personal practice.",
      "description": "Magical product for personal practice.",
      "fullDescription": "Magical product for personal practice."
    },
    "sumka-shopper-drevo": {
      "title": "Bag Shopper Drevo",
      "shortDescription": "Magical product for personal practice.",
      "description": "Magical product for personal practice.",
      "fullDescription": "Magical product for personal practice."
    },
    "altarnaya-podstavka-drevo": {
      "title": "Altar Stand Drevo",
      "shortDescription": "Magical product for personal practice.",
      "description": "Magical product for personal practice.",
      "fullDescription": "Magical product for personal practice."
    },
    "sumka-shopper-vedma": {
      "title": "Bag Shopper Vedma",
      "shortDescription": "Magical product for personal practice.",
      "description": "Magical product for personal practice.",
      "fullDescription": "Magical product for personal practice."
    },
    "shpilka-dlya-volos-mech": {
      "title": "Shpilka For Volos Mech",
      "shortDescription": "Magical product for personal practice.",
      "description": "Magical product for personal practice.",
      "fullDescription": "Magical product for personal practice."
    },
    "altarnoe-pokryvalo-2": {
      "title": "Altar Cloth",
      "shortDescription": "Magical product for personal practice.",
      "description": "Magical product for personal practice.",
      "fullDescription": "Magical product for personal practice."
    },
    "shpilka-dlya-volos-zvezda": {
      "title": "Shpilka For Volos Zvezda",
      "shortDescription": "Magical product for personal practice.",
      "description": "Magical product for personal practice.",
      "fullDescription": "Magical product for personal practice."
    },
    "altarnoe-pokryvalo-3": {
      "title": "Altar Cloth",
      "shortDescription": "Magical product for personal practice.",
      "description": "Magical product for personal practice.",
      "fullDescription": "Magical product for personal practice."
    },
    "shpilka-dlya-volos-siyanie": {
      "title": "Shpilka For Volos Siyanie",
      "shortDescription": "Magical product for personal practice.",
      "description": "Magical product for personal practice.",
      "fullDescription": "Magical product for personal practice."
    },
    "altarnoe-pokryvalo-4": {
      "title": "Altar Cloth",
      "shortDescription": "Magical product for personal practice.",
      "description": "Magical product for personal practice.",
      "fullDescription": "Magical product for personal practice."
    },
    "shpilka-dlya-volos-luna": {
      "title": "Shpilka For Volos Luna",
      "shortDescription": "Magical product for personal practice.",
      "description": "Magical product for personal practice.",
      "fullDescription": "Magical product for personal practice."
    },
    "altarnoe-pokryvalo-5": {
      "title": "Altar Cloth",
      "shortDescription": "Magical product for personal practice.",
      "description": "Magical product for personal practice.",
      "fullDescription": "Magical product for personal practice."
    },
    "braslet": {
      "title": "Bracelet",
      "shortDescription": "Handmade bracelet for personal practice and everyday wear.",
      "description": "Handmade bracelet for personal practice and everyday wear.",
      "fullDescription": "Handmade bracelet for personal practice and everyday wear."
    },
    "altarnoe-pokryvalo-6": {
      "title": "Altar Cloth",
      "shortDescription": "Magical product for personal practice.",
      "description": "Magical product for personal practice.",
      "fullDescription": "Magical product for personal practice."
    },
    "braslet-2": {
      "title": "Bracelet",
      "shortDescription": "Handmade bracelet for personal practice and everyday wear.",
      "description": "Handmade bracelet for personal practice and everyday wear.",
      "fullDescription": "Handmade bracelet for personal practice and everyday wear."
    },
    "altarnoe-pokryvalo-7": {
      "title": "Altar Cloth",
      "shortDescription": "Magical product for personal practice.",
      "description": "Magical product for personal practice.",
      "fullDescription": "Magical product for personal practice."
    },
    "podstavka-dlya-altarya-santa-muerte": {
      "title": "Stand For Altarya Santa Muerte",
      "shortDescription": "Magical product for personal practice.",
      "description": "Magical product for personal practice.",
      "fullDescription": "Magical product for personal practice."
    },
    "sergi-sleza-vampira": {
      "title": "Earrings Sleza Vampira",
      "shortDescription": "Magical product for personal practice.",
      "description": "Magical product for personal practice.",
      "fullDescription": "Magical product for personal practice."
    },
    "podstavka-dlya-altarya-santa-muerte-2": {
      "title": "Stand For Altarya Santa Muerte",
      "shortDescription": "Magical product for personal practice.",
      "description": "Magical product for personal practice.",
      "fullDescription": "Magical product for personal practice."
    },
    "sergi-sila-vedmy": {
      "title": "Earrings Power Vedmy",
      "shortDescription": "Magical product for personal practice.",
      "description": "Magical product for personal practice.",
      "fullDescription": "Magical product for personal practice."
    },
    "braslet-iz-koshachego-glaza": {
      "title": "Bracelet From Cat's eye Eye",
      "shortDescription": "Handmade bracelet for personal practice and everyday wear.",
      "description": "Handmade bracelet for personal practice and everyday wear.",
      "fullDescription": "Handmade bracelet for personal practice and everyday wear."
    },
    "pridvernyy-kovrik-blagoslovenie-i-zaschita-doma": {
      "title": "Pridverny Mat Blagoslovenie I Zaschita Doma",
      "shortDescription": "Magical product for personal practice.",
      "description": "Magical product for personal practice.",
      "fullDescription": "Magical product for personal practice."
    },
    "podstavka-dlya-altarya-sila-i-zaschita-drakona": {
      "title": "Stand For Altarya Power I Zaschita Drakona",
      "shortDescription": "Thoughtful magical gift or souvenir.",
      "description": "Thoughtful magical gift or souvenir.",
      "fullDescription": "Thoughtful magical gift or souvenir."
    },
    "braslet-iz-flyuorita": {
      "title": "Bracelet From Fluorite",
      "shortDescription": "Handmade bracelet for personal practice and everyday wear.",
      "description": "Handmade bracelet for personal practice and everyday wear.",
      "fullDescription": "Handmade bracelet for personal practice and everyday wear."
    },
    "podstavka-dlya-altarya-oko-drakona": {
      "title": "Stand For Altarya Oko Drakona",
      "shortDescription": "Thoughtful magical gift or souvenir.",
      "description": "Thoughtful magical gift or souvenir.",
      "fullDescription": "Thoughtful magical gift or souvenir."
    },
    "braslet-iz-agata-veny-drakona": {
      "title": "Bracelet From Agate Veny Drakona",
      "shortDescription": "Handmade bracelet for personal practice and everyday wear.",
      "description": "Handmade bracelet for personal practice and everyday wear.",
      "fullDescription": "Handmade bracelet for personal practice and everyday wear."
    },
    "podstavka-dlya-altarya-oko-drakona-2": {
      "title": "Stand For Altarya Oko Drakona",
      "shortDescription": "Thoughtful magical gift or souvenir.",
      "description": "Thoughtful magical gift or souvenir.",
      "fullDescription": "Thoughtful magical gift or souvenir."
    },
    "braslet-bychiy-glaz-s-agatom": {
      "title": "Bracelet Bychiy Glaz S Agatom",
      "shortDescription": "Handmade bracelet for personal practice and everyday wear.",
      "description": "Handmade bracelet for personal practice and everyday wear.",
      "fullDescription": "Handmade bracelet for personal practice and everyday wear."
    },
    "braslet-iz-ametista": {
      "title": "Bracelet From Amethyst",
      "shortDescription": "Handmade bracelet for personal practice and everyday wear.",
      "description": "Handmade bracelet for personal practice and everyday wear.",
      "fullDescription": "Handmade bracelet for personal practice and everyday wear."
    },
    "braslet-iz-gematita": {
      "title": "Bracelet From Gematita",
      "shortDescription": "Handmade bracelet for personal practice and everyday wear.",
      "description": "Handmade bracelet for personal practice and everyday wear.",
      "fullDescription": "Handmade bracelet for personal practice and everyday wear."
    },
    "braslet-iz-glazkovogo-agata": {
      "title": "Bracelet From Glazkovogo Agate",
      "shortDescription": "Handmade bracelet for personal practice and everyday wear.",
      "description": "Handmade bracelet for personal practice and everyday wear.",
      "fullDescription": "Handmade bracelet for personal practice and everyday wear."
    }
  }
}
